
  {
    "_id": 1,
    "title": "Long Nose DOG",
    "points": 420,
    "question": "What type of dog is this?",
    "answer": "Borzoi",
    "image": "http://127.0.0.1:4000/images/longdog.jpg"
  }
  
  
  
  
  {
    "_id": 2,
    "title": "Dylan",
    "points": 421,
    "question": "Who Is this?",
    "answer": "Dylan",
    "image": "http://127.0.0.1:4000/images/dylan.jpg"
  }
  {
    "_id": 3,
    "title": "SpongeBob",
    "points": 1,
    "question": "Who is the character in this image?",
    "answer": "SpongeBob",
    "image": "http://127.0.0.1:4000/images/sponge.jpg"
  }

  
